CHANGES.rst
CONTRIBUTORS.rst
DEVELOP.rst
LICENSE.GPL
LICENSE.rst
MANIFEST.in
README.rst
setup.cfg
setup.py
docs/UPGRADE.txt
docs/conf.py
docs/index.rst
src/collective/__init__.py
src/collective.js.jqueryui.egg-info/PKG-INFO
src/collective.js.jqueryui.egg-info/SOURCES.txt
src/collective.js.jqueryui.egg-info/dependency_links.txt
src/collective.js.jqueryui.egg-info/entry_points.txt
src/collective.js.jqueryui.egg-info/namespace_packages.txt
src/collective.js.jqueryui.egg-info/not-zip-safe
src/collective.js.jqueryui.egg-info/requires.txt
src/collective.js.jqueryui.egg-info/top_level.txt
src/collective/js/__init__.py
src/collective/js/jqueryui/__init__.py
src/collective/js/jqueryui/common.zcml
src/collective/js/jqueryui/config.py
src/collective/js/jqueryui/configure.zcml
src/collective/js/jqueryui/controlpanel.pt
src/collective/js/jqueryui/controlpanel.py
src/collective/js/jqueryui/controlpanel_layout.pt
src/collective/js/jqueryui/interfaces.py
src/collective/js/jqueryui/jquery-ui-1.10.4.custom.js
src/collective/js/jqueryui/jquery-ui-1.10.4.custom.min.js
src/collective/js/jqueryui/jquery-ui-i18n.js
src/collective/js/jqueryui/jqueryui_icon.jpg
src/collective/js/jqueryui/plone.zcml
src/collective/js/jqueryui/profiles.zcml
src/collective/js/jqueryui/resources.py
src/collective/js/jqueryui/setuphandlers.py
src/collective/js/jqueryui/testing.py
src/collective/js/jqueryui/upgrades.py
src/collective/js/jqueryui/utils.py
src/collective/js/jqueryui/viewlet.py
src/collective/js/jqueryui/zope.zcml
src/collective/js/jqueryui/css/sunburst-patch.css
src/collective/js/jqueryui/css/sunburst/jqueryui.css
src/collective/js/jqueryui/css/sunburst/images/animated-overlay.gif
src/collective/js/jqueryui/css/sunburst/images/ui-bg_flat_100_ffffff_40x100.png
src/collective/js/jqueryui/css/sunburst/images/ui-bg_flat_45_205c90_40x100.png
src/collective/js/jqueryui/css/sunburst/images/ui-bg_flat_45_ffddcc_40x100.png
src/collective/js/jqueryui/css/sunburst/images/ui-bg_flat_50_75ad0a_40x100.png
src/collective/js/jqueryui/css/sunburst/images/ui-bg_flat_55_999999_40x100.png
src/collective/js/jqueryui/css/sunburst/images/ui-bg_flat_55_ffdd77_40x100.png
src/collective/js/jqueryui/css/sunburst/images/ui-bg_flat_75_aaaaaa_40x100.png
src/collective/js/jqueryui/css/sunburst/images/ui-bg_flat_75_dddddd_40x100.png
src/collective/js/jqueryui/css/sunburst/images/ui-icons_205c90_256x240.png
