Metadata-Version: 2.1
Name: collective.js.jqueryui
Version: 2.2.0
Summary: JQueryUI ready for Plone
Home-page: https://github.com/collective/collective.js.jqueryui
Author: JeanMichel FRANCOIS aka toutpt
Author-email: toutpt@gmail.com
License: GPL version 2
Project-URL: PyPI, https://pypi.python.org/pypi/collective.js.jqueryui
Project-URL: Source, https://github.com/collective/collective.js.jqueryui
Project-URL: Tracker, https://github.com/collective/collective.js.jqueryui/issues
Keywords: plone jqueryui
Classifier: Development Status :: 6 - Mature
Classifier: Environment :: Web Environment
Classifier: License :: OSI Approved :: GNU General Public License (GPL)
Classifier: Operating System :: OS Independent
Classifier: Framework :: Zope2
Classifier: Framework :: Zope :: 2
Classifier: Framework :: Zope :: 4
Classifier: Framework :: Plone
Classifier: Framework :: Plone :: Addon
Classifier: Framework :: Plone :: 4.3
Classifier: Framework :: Plone :: 5.0
Classifier: Framework :: Plone :: 5.1
Classifier: Framework :: Plone :: 5.2
Classifier: Programming Language :: Python
Classifier: Programming Language :: Python :: 2.7
Classifier: Programming Language :: Python :: 3.6
Classifier: Programming Language :: Python :: 3.7
Requires-Python: >=2.7
Provides-Extra: test
License-File: LICENSE.GPL
License-File: LICENSE.rst
